periodictablecode/periodictablecode.py
periodictablecode-0.1.0.dist-info/LICENSE
periodictablecode-0.1.0.dist-info/METADATA
periodictablecode-0.1.0.dist-info/WHEEL
periodictablecode-0.1.0.dist-info/top_level.txt
periodictablecode-0.1.0.dist-info/RECORD
