Metadata-Version: 2.1
Name: periodictablecode
Version: 0.1.0
Summary: Encrypting strings using the periodic table
Home-page: https://github.com/Sam-Nielsen-Dot/periodictablecode
Author: Sam Nielsen
Author-email: lenssimane@gmail.com
License: MIT
Platform: UNKNOWN
Classifier: Development Status :: 1 - Planning
Classifier: Intended Audience :: Healthcare Industry
Classifier: Environment :: Win32 (MS Windows)
Classifier: License :: OSI Approved :: MIT License
Classifier: Natural Language :: English
Classifier: Programming Language :: Python :: 2
Classifier: Programming Language :: Python :: 2.7
Classifier: Programming Language :: Python :: 3
Classifier: Programming Language :: Python :: 3.4
Classifier: Programming Language :: Python :: 3.5
License-File: LICENSE
